odoo/addons/account_cutoff_accrual_order_base/README.rst
odoo/addons/account_cutoff_accrual_order_base/__init__.py
odoo/addons/account_cutoff_accrual_order_base/__manifest__.py
odoo/addons/account_cutoff_accrual_order_base/i18n/account_cutoff_accrual_order_base.pot
odoo/addons/account_cutoff_accrual_order_base/i18n/fr.po
odoo/addons/account_cutoff_accrual_order_base/i18n/it.po
odoo/addons/account_cutoff_accrual_order_base/models/__init__.py
odoo/addons/account_cutoff_accrual_order_base/models/account_cutoff.py
odoo/addons/account_cutoff_accrual_order_base/models/account_cutoff_line.py
odoo/addons/account_cutoff_accrual_order_base/models/account_move.py
odoo/addons/account_cutoff_accrual_order_base/models/order_line_mixin.py
odoo/addons/account_cutoff_accrual_order_base/readme/CONFIGURE.rst
odoo/addons/account_cutoff_accrual_order_base/readme/CONTRIBUTORS.rst
odoo/addons/account_cutoff_accrual_order_base/readme/DESCRIPTION.rst
odoo/addons/account_cutoff_accrual_order_base/static/description/icon.png
odoo/addons/account_cutoff_accrual_order_base/static/description/index.html
odoo/addons/account_cutoff_accrual_order_base/tests/__init__.py
odoo/addons/account_cutoff_accrual_order_base/tests/common.py
odoo/addons/account_cutoff_accrual_order_base/views/account_cutoff_line_view.xml
odoo/addons/account_cutoff_accrual_order_base/views/account_cutoff_view.xml
odoo_addon_account_cutoff_accrual_order_base-16.0.1.1.0.dist-info/METADATA
odoo_addon_account_cutoff_accrual_order_base-16.0.1.1.0.dist-info/WHEEL
odoo_addon_account_cutoff_accrual_order_base-16.0.1.1.0.dist-info/top_level.txt
odoo_addon_account_cutoff_accrual_order_base-16.0.1.1.0.dist-info/RECORD
